teby/__init__.py
teby-0.0.2.dist-info/METADATA
teby-0.0.2.dist-info/WHEEL
teby-0.0.2.dist-info/entry_points.txt
teby-0.0.2.dist-info/top_level.txt
teby-0.0.2.dist-info/RECORD
