Metadata-Version: 2.1
Name: teby
Version: 0.0.2
Summary: A simple Python library
Author-email: Ning Ren <renning22@gmail.com>
Maintainer-email: Ning Ren <renning22@gmail.com>
Project-URL: Homepage, https://github.com/renning22/teby
Project-URL: Bug Reports, https://github.com/renning22/teby/issues
Project-URL: Funding, https://github.com/renning22/teby
Project-URL: Say Thanks!, https://github.com/renning22/teby
Project-URL: Source, https://github.com/renning22/teby
Keywords: setuptools,development
Classifier: Development Status :: 3 - Alpha
Classifier: Intended Audience :: Developers
Classifier: Topic :: Software Development :: Build Tools
Classifier: License :: OSI Approved :: MIT License
Classifier: Programming Language :: Python :: 3
Classifier: Programming Language :: Python :: 3.7
Classifier: Programming Language :: Python :: 3.8
Classifier: Programming Language :: Python :: 3.9
Classifier: Programming Language :: Python :: 3.10
Classifier: Programming Language :: Python :: 3.11
Classifier: Programming Language :: Python :: 3 :: Only
Requires-Python: >=3.7
Requires-Dist: ray[default]
Provides-Extra: dev
Requires-Dist: check-manifest; extra == "dev"
Provides-Extra: test
Requires-Dist: coverage; extra == "test"
